apoplan/__init__.py
apoplan/apoplan-cli
apoplan/classes.py
apoplan/cli.py
apoplan/decorators.py
apoplan/protobufs/__init__.py
apoplan/protobufs/bauplan_pb2.py
apoplan/protobufs/bauplan_pb2.pyi
apoplan/protobufs/bauplan_pb2_grpc.py
apoplan/protobufs/execution_plan_pb2.py
apoplan/protobufs/execution_plan_pb2.pyi
apoplan/protobufs/execution_plan_pb2_grpc.py
apoplan/protobufs/python/__init__.py
apoplan/protobufs/python/bauplan_pb2.py
apoplan/protobufs/python/bauplan_pb2.pyi
apoplan/protobufs/python/bauplan_pb2_grpc.py
apoplan/protobufs/python/execution_plan_pb2.py
apoplan/protobufs/python/execution_plan_pb2.pyi
apoplan/protobufs/python/execution_plan_pb2_grpc.py
apoplan/protobufs/python/runner_service_pb2.py
apoplan/protobufs/python/runner_service_pb2.pyi
apoplan/protobufs/python/runner_service_pb2_grpc.py
apoplan/protobufs/python/runner_task_pb2.py
apoplan/protobufs/python/runner_task_pb2.pyi
apoplan/protobufs/python/runner_task_pb2_grpc.py
apoplan/protobufs/runner_service_pb2.py
apoplan/protobufs/runner_service_pb2.pyi
apoplan/protobufs/runner_service_pb2_grpc.py
apoplan/protobufs/runner_task_pb2.py
apoplan/protobufs/runner_task_pb2.pyi
apoplan/protobufs/runner_task_pb2_grpc.py
apoplan/py.typed
apoplan/query.py
apoplan/standard_expectations.py
apoplan-0.0.3a33.dist-info/METADATA
apoplan-0.0.3a33.dist-info/WHEEL
apoplan-0.0.3a33.dist-info/entry_points.txt
apoplan-0.0.3a33.dist-info/RECORD
