Metadata-Version: 2.1
Name: apoplan
Version: 0.0.3a33
Summary: Bauplan CLI
Author: Jacopo Tagliabue
Author-email: jacopo.tagliabue@bauplanlabs.com
Requires-Python: >=3.8,<4.0
Classifier: Programming Language :: Python :: 3
Classifier: Programming Language :: Python :: 3.8
Classifier: Programming Language :: Python :: 3.9
Classifier: Programming Language :: Python :: 3.10
Classifier: Programming Language :: Python :: 3.11
Requires-Dist: grpcio (>=1.59.0,<2.0.0)
Requires-Dist: opentelemetry-proto (>=1.20.0,<2.0.0)
Requires-Dist: protobuf (>=4.24.4,<5.0.0)
Requires-Dist: pyarrow (>=14.0.0,<15.0.0)
Requires-Dist: pyyaml (>=6.0.1,<7.0.0)
